gslmathieu
